{
  "info": {
    "description": "data",
    "version": "1.0",
    "year": 2025,
    "contributor": "search engine",
    "source": "augmented",
    "license": {
      "name": "Creative Commons Attribution 4.0 International",
      "url": "https://creativecommons.org/licenses/by/4.0/"
    }
  },
  "images": [
    {
      "id": 4900168220,
      "width": 256,
      "height": 256,
      "file_name": "image (664).JPG",
      "size": 19336,
      "format": "JPG",
      "url": "",
      "hash": "",
      "status": "success"
    }
  ],
  "annotations": [
    {
      "id": 2161016232,
      "image_id": 4900168220,
      "category_id": 1000000027,
      "segmentation": [],
      "area": 2500,
      "bbox": [
        5,
        63,
        115,
        166
      ]
    },
    {
      "id": 1667798232,
      "image_id": 4900168220,
      "category_id": 1000000027,
      "segmentation": [],
      "area": 183,
      "bbox": [
        140,
        198,
        22,
        26
      ]
    },
    {
      "id": 1892284232,
      "image_id": 4900168220,
      "category_id": 1000000027,
      "segmentation": [],
      "area": 178,
      "bbox": [
        127,
        183,
        17,
        23
      ]
    },
    {
      "id": 5315516232,
      "image_id": 4900168220,
      "category_id": 1000000027,
      "segmentation": [],
      "area": 126,
      "bbox": [
        109,
        166,
        12,
        19
      ]
    },
    {
      "id": 1947904232,
      "image_id": 4900168220,
      "category_id": 1000000027,
      "segmentation": [],
      "area": 367,
      "bbox": [
        132,
        161,
        34,
        25
      ]
    },
    {
      "id": 4051929232,
      "image_id": 4900168220,
      "category_id": 1000000027,
      "segmentation": [],
      "area": 628,
      "bbox": [
        46,
        128,
        30,
        55
      ]
    },
    {
      "id": 6909364232,
      "image_id": 4900168220,
      "category_id": 1000000027,
      "segmentation": [],
      "area": 156,
      "bbox": [
        87,
        160,
        21,
        20
      ]
    },
    {
      "id": 2661984232,
      "image_id": 4900168220,
      "category_id": 1000000027,
      "segmentation": [],
      "area": 180,
      "bbox": [
        192,
        128,
        20,
        23
      ]
    },
    {
      "id": 4376222232,
      "image_id": 4900168220,
      "category_id": 1000000027,
      "segmentation": [],
      "area": 107,
      "bbox": [
        103,
        132,
        17,
        17
      ]
    },
    {
      "id": 5922317232,
      "image_id": 4900168220,
      "category_id": 1000000027,
      "segmentation": [],
      "area": 248,
      "bbox": [
        44,
        96,
        17,
        31
      ]
    },
    {
      "id": 2383215232,
      "image_id": 4900168220,
      "category_id": 1000000027,
      "segmentation": [],
      "area": 1216,
      "bbox": [
        47,
        18,
        54,
        52
      ]
    },
    {
      "id": 3842345232,
      "image_id": 4900168220,
      "category_id": 1000000027,
      "segmentation": [],
      "area": 246,
      "bbox": [
        191,
        47,
        27,
        17
      ]
    },
    {
      "id": 7782546232,
      "image_id": 4900168220,
      "category_id": 1000000027,
      "segmentation": [],
      "area": 286,
      "bbox": [
        176,
        28,
        51,
        29
      ]
    },
    {
      "id": 3428459232,
      "image_id": 4900168220,
      "category_id": 1000000027,
      "segmentation": [],
      "area": 334,
      "bbox": [
        104,
        22,
        55,
        16
      ]
    }
  ],
  "categories": [
    {
      "id": 1000000027,
      "name": "Leaf_scorch",
      "supercategory": "Strawberry"
    }
  ]
}