{
  "info": {
    "description": "data",
    "version": "1.0",
    "year": 2025,
    "contributor": "search engine",
    "source": "no_augmentation",
    "license": {
      "name": "Creative Commons Attribution 4.0 International",
      "url": "https://creativecommons.org/licenses/by/4.0/"
    },
    "leaf_info": {
      "leaf_number": 72.0,
      "source": "plant_village_classification",
      "original_filename": "RS_L.Scorch 1585.JPG"
    }
  },
  "images": [
    {
      "id": 2151967040,
      "width": 256,
      "height": 256,
      "file_name": "image (840).JPG",
      "size": 21983,
      "format": "JPG",
      "url": "",
      "hash": "",
      "status": "success",
      "original_filename": "RS_L.Scorch 1585.JPG",
      "pvc_filename": "bfe9051f-57f9-418c-880d-6b6aee0130c0___RS_L.Scorch 1585.JPG"
    }
  ],
  "annotations": [
    {
      "id": 9910450048,
      "image_id": 2151967040,
      "category_id": 2000000027,
      "segmentation": [],
      "area": 260,
      "bbox": [
        165,
        218,
        20,
        29
      ]
    },
    {
      "id": 6515542048,
      "image_id": 2151967040,
      "category_id": 2000000027,
      "segmentation": [],
      "area": 18175,
      "bbox": [
        36,
        22,
        175,
        205
      ]
    },
    {
      "id": 7486170048,
      "image_id": 2151967040,
      "category_id": 2000000027,
      "segmentation": [],
      "area": 263,
      "bbox": [
        81,
        170,
        16,
        38
      ]
    },
    {
      "id": 8220306048,
      "image_id": 2151967040,
      "category_id": 2000000027,
      "segmentation": [],
      "area": 155,
      "bbox": [
        174,
        71,
        15,
        19
      ]
    }
  ],
  "categories": [
    {
      "id": 2000000027,
      "name": "Leaf_scorch",
      "supercategory": "Strawberry"
    }
  ]
}